gbarrier/__init__.py
gbarrier/main.py
gbarrier-0.0.2.dist-info/LICENSE
gbarrier-0.0.2.dist-info/METADATA
gbarrier-0.0.2.dist-info/WHEEL
gbarrier-0.0.2.dist-info/top_level.txt
gbarrier-0.0.2.dist-info/RECORD
